{
	"credit": "Made with Blockbench",
	"texture_size": [128, 128],
	"textures": {
		"0": "custom/props/trashbin",
		"particle": "custom/props/trashbin"
	},
	"elements": [
		{
			"from": [-8.892, 8.8259, 6.48142],
			"to": [-6.392, 9.6419, 7.28942],
			"rotation": {"angle": 0, "axis": "x", "origin": [8, 8.70682, 5.85736], "rescale": true},
			"faces": {
				"north": {"uv": [7.75, 4.125, 8.125, 4.25], "texture": "#0"},
				"east": {"uv": [3.75, 12.5, 3.875, 12.625], "texture": "#0"},
				"south": {"uv": [3.25, 9.75, 3.625, 9.875], "texture": "#0"},
				"west": {"uv": [7, 12.5, 7.125, 12.625], "texture": "#0"},
				"up": {"uv": [12.75, 11.375, 12.375, 11.25], "texture": "#0"},
				"down": {"uv": [12.75, 11.375, 12.375, 11.5], "texture": "#0"}
			}
		},
		{
			"from": [22.392, 9.0759, 6.48142],
			"to": [24.892, 9.8919, 7.28942],
			"rotation": {"angle": 0, "axis": "x", "origin": [8, 8.95682, 5.85736], "rescale": true},
			"faces": {
				"north": {"uv": [8.125, 4.125, 7.75, 4.25], "texture": "#0"},
				"east": {"uv": [7.125, 12.5, 7, 12.625], "texture": "#0"},
				"south": {"uv": [3.625, 9.75, 3.25, 9.875], "texture": "#0"},
				"west": {"uv": [3.875, 12.5, 3.75, 12.625], "texture": "#0"},
				"up": {"uv": [12.375, 11.375, 12.75, 11.25], "texture": "#0"},
				"down": {"uv": [12.375, 11.375, 12.75, 11.5], "texture": "#0"}
			}
		},
		{
			"from": [-8.642, 8.89847, 5.30761],
			"to": [-7.892, 11.71447, 8.11561],
			"rotation": {"angle": 45, "axis": "x", "origin": [8, 8.95682, 5.85736]},
			"faces": {
				"north": {"uv": [12.375, 10.5, 12.5, 10.875], "texture": "#0"},
				"east": {"uv": [3.875, 6.25, 4.25, 6.625], "texture": "#0"},
				"south": {"uv": [12.375, 10.875, 12.5, 11.25], "texture": "#0"},
				"west": {"uv": [3.875, 11.875, 4.25, 12.25], "texture": "#0"},
				"up": {"uv": [12.5, 12.125, 12.375, 11.75], "texture": "#0"},
				"down": {"uv": [2.25, 12.5, 2.125, 12.875], "texture": "#0"}
			}
		},
		{
			"from": [23.892, 8.89847, 5.30761],
			"to": [24.642, 11.71447, 8.11561],
			"rotation": {"angle": 45, "axis": "x", "origin": [8, 8.95682, 5.85736]},
			"faces": {
				"north": {"uv": [12.5, 10.5, 12.375, 10.875], "texture": "#0"},
				"east": {"uv": [4.25, 11.875, 3.875, 12.25], "texture": "#0"},
				"south": {"uv": [12.5, 10.875, 12.375, 11.25], "texture": "#0"},
				"west": {"uv": [4.25, 6.25, 3.875, 6.625], "texture": "#0"},
				"up": {"uv": [12.375, 12.125, 12.5, 11.75], "texture": "#0"},
				"down": {"uv": [2.125, 12.5, 2.25, 12.875], "texture": "#0"}
			}
		},
		{
			"from": [-8.61, 7.29551, 7.41858],
			"to": [-7.86, 11.29551, 16.41858],
			"rotation": {"angle": 0, "axis": "x", "origin": [8, 8.95682, 5.85736]},
			"faces": {
				"north": {"uv": [0.625, 12.375, 0.75, 12.875], "texture": "#0"},
				"east": {"uv": [12, 2, 13.125, 2.5], "texture": "#0"},
				"south": {"uv": [0.75, 12.375, 0.875, 12.875], "texture": "#0"},
				"west": {"uv": [12, 2.5, 13.125, 3], "texture": "#0"},
				"up": {"uv": [2.125, 13.375, 2, 12.25], "texture": "#0"},
				"down": {"uv": [6.25, 12.25, 6.125, 13.375], "texture": "#0"}
			}
		},
		{
			"from": [23.86, 7.29551, 7.41858],
			"to": [24.61, 11.29551, 16.41858],
			"rotation": {"angle": 0, "axis": "x", "origin": [8, 8.95682, 5.85736]},
			"faces": {
				"north": {"uv": [0.75, 12.375, 0.625, 12.875], "texture": "#0"},
				"east": {"uv": [13.125, 2.5, 12, 3], "texture": "#0"},
				"south": {"uv": [0.875, 12.375, 0.75, 12.875], "texture": "#0"},
				"west": {"uv": [13.125, 2, 12, 2.5], "texture": "#0"},
				"up": {"uv": [2, 13.375, 2.125, 12.25], "texture": "#0"},
				"down": {"uv": [6.125, 12.25, 6.25, 13.375], "texture": "#0"}
			}
		},
		{
			"from": [-8.642, 15.25, 8.75],
			"to": [-7.892, 18.75, 14.5],
			"rotation": {"angle": 45, "axis": "x", "origin": [8, 8.95682, 5.85736]},
			"faces": {
				"north": {"uv": [3.75, 8.25, 3.875, 8.75], "texture": "#0"},
				"east": {"uv": [12, 3.5, 12.75, 4], "texture": "#0"},
				"south": {"uv": [0.5, 12.375, 0.625, 12.875], "texture": "#0"},
				"west": {"uv": [8.75, 12.125, 9.5, 12.625], "texture": "#0"},
				"up": {"uv": [8.125, 13, 8, 12.25], "texture": "#0"},
				"down": {"uv": [12.125, 12.25, 12, 13], "texture": "#0"}
			}
		},
		{
			"from": [23.892, 15.25, 8.75],
			"to": [24.642, 18.75, 14.5],
			"rotation": {"angle": 45, "axis": "x", "origin": [8, 8.95682, 5.85736]},
			"faces": {
				"north": {"uv": [3.875, 8.25, 3.75, 8.75], "texture": "#0"},
				"east": {"uv": [9.5, 12.125, 8.75, 12.625], "texture": "#0"},
				"south": {"uv": [0.625, 12.375, 0.5, 12.875], "texture": "#0"},
				"west": {"uv": [12.75, 3.5, 12, 4], "texture": "#0"},
				"up": {"uv": [8, 13, 8.125, 12.25], "texture": "#0"},
				"down": {"uv": [12, 12.25, 12.125, 13], "texture": "#0"}
			}
		},
		{
			"from": [-9.125, 18.75, 0.5],
			"to": [-7.625, 20.25, 14.75],
			"rotation": {"angle": 45, "axis": "x", "origin": [8, 8.95682, 5.85736]},
			"faces": {
				"north": {"uv": [1.625, 12.375, 1.875, 12.625], "texture": "#0"},
				"east": {"uv": [12, 3, 13.75, 3.25], "texture": "#0"},
				"south": {"uv": [3.875, 12.375, 4.125, 12.625], "texture": "#0"},
				"west": {"uv": [12, 3.25, 13.75, 3.5], "texture": "#0"},
				"up": {"uv": [8, 4.125, 7.75, 2.375], "texture": "#0"},
				"down": {"uv": [8.25, 2.375, 8, 4.125], "texture": "#0"}
			}
		},
		{
			"from": [23.625, 18.75, 0.5],
			"to": [25.125, 20.25, 14.75],
			"rotation": {"angle": 45, "axis": "x", "origin": [8, 8.95682, 5.85736]},
			"faces": {
				"north": {"uv": [1.875, 12.375, 1.625, 12.625], "texture": "#0"},
				"east": {"uv": [13.75, 3.25, 12, 3.5], "texture": "#0"},
				"south": {"uv": [4.125, 12.375, 3.875, 12.625], "texture": "#0"},
				"west": {"uv": [13.75, 3, 12, 3.25], "texture": "#0"},
				"up": {"uv": [7.75, 4.125, 8, 2.375], "texture": "#0"},
				"down": {"uv": [8, 2.375, 8.25, 4.125], "texture": "#0"}
			}
		},
		{
			"from": [-8.75, 19, -3],
			"to": [24.75, 21.75, 17.25],
			"rotation": {"angle": 45, "axis": "x", "origin": [8, 8.95682, 5.85736]},
			"faces": {
				"north": {"uv": [8.125, 11.75, 12.375, 12.125], "texture": "#0"},
				"east": {"uv": [12, 0.75, 14.5, 1.125], "texture": "#0"},
				"south": {"uv": [11.75, 4, 16, 4.375], "texture": "#0"},
				"west": {"uv": [12, 1.125, 14.5, 1.5], "texture": "#0"},
				"up": {"uv": [4.25, 2.5, 0, 0], "texture": "#0"},
				"down": {"uv": [4.25, 2.5, 0, 5], "texture": "#0"}
			}
		},
		{
			"from": [-7.587, 16.8422, 16.49838],
			"to": [23.587, 22.0922, 19.97838],
			"rotation": {"angle": 22.5, "axis": "x", "origin": [7.936, 8.95682, 5.85736]},
			"faces": {
				"north": {"uv": [8.25, 9.875, 12.25, 10.5], "texture": "#0"},
				"east": {"uv": [3.875, 5, 4.25, 5.625], "texture": "#0"},
				"south": {"uv": [8.25, 10.5, 12.25, 11.125], "texture": "#0"},
				"west": {"uv": [3.875, 5.625, 4.25, 6.25], "texture": "#0"},
				"up": {"uv": [15.75, 4.75, 11.75, 4.375], "texture": "#0"},
				"down": {"uv": [15.75, 4.75, 11.75, 5.125], "texture": "#0"}
			}
		},
		{
			"from": [-7.491, 17.12387, 14.79731],
			"to": [23.491, 20.46387, 17.79731],
			"rotation": {"angle": -22.5, "axis": "x", "origin": [7.936, 8.95682, 5.85736]},
			"faces": {
				"north": {"uv": [15.75, 7, 11.75, 7.375], "rotation": 180, "texture": "#0"},
				"east": {"uv": [6.25, 12.25, 6.625, 12.625], "rotation": 270, "texture": "#0"},
				"south": {"uv": [15.75, 7, 11.75, 6.625], "texture": "#0"},
				"west": {"uv": [6.625, 12.25, 7, 12.625], "rotation": 90, "texture": "#0"},
				"up": {"uv": [11.75, 5.125, 15.75, 5.5], "rotation": 180, "texture": "#0"},
				"down": {"uv": [11.75, 5.5, 15.75, 5.875], "texture": "#0"}
			}
		},
		{
			"from": [-7.475, 21.19635, 6.16346],
			"to": [23.475, 25.53635, 11.66346],
			"rotation": {"angle": 22.5, "axis": "x", "origin": [7.936, 8.95682, 5.85736]},
			"faces": {
				"north": {"uv": [4.25, 11.25, 8.25, 11.75], "texture": "#0"},
				"east": {"uv": [9.5, 12.125, 10.25, 12.625], "texture": "#0"},
				"south": {"uv": [11.5, 7.75, 15.5, 8.25], "texture": "#0"},
				"west": {"uv": [10.25, 12.125, 11, 12.625], "texture": "#0"},
				"up": {"uv": [12.25, 6.625, 8.25, 5.875], "texture": "#0"},
				"down": {"uv": [8.25, 9.875, 4.25, 10.625], "texture": "#0"}
			}
		},
		{
			"from": [-7.555, 21.65621, 4.87679],
			"to": [23.555, 26.49621, 13.87679],
			"rotation": {"angle": 45, "axis": "x", "origin": [7.936, 8.95682, 5.85736]},
			"faces": {
				"north": {"uv": [4.25, 10.625, 8.25, 11.25], "texture": "#0"},
				"east": {"uv": [2.125, 9.25, 3.25, 9.875], "texture": "#0"},
				"south": {"uv": [8.25, 11.125, 12.25, 11.75], "texture": "#0"},
				"west": {"uv": [2.125, 11.875, 3.25, 12.5], "texture": "#0"},
				"up": {"uv": [11.75, 7.75, 7.75, 6.625], "texture": "#0"},
				"down": {"uv": [7.75, 8.75, 3.75, 9.875], "texture": "#0"}
			}
		},
		{
			"from": [-4.84, -4.974, -1.436],
			"to": [-3.59, -0.974, 2.564],
			"rotation": {"angle": 0, "axis": "y", "origin": [-4.24125, -1.77178, 1.1904]},
			"faces": {
				"north": {"uv": [0.875, 12.375, 1, 12.875], "texture": "#0"},
				"east": {"uv": [3.25, 9.25, 3.75, 9.75], "texture": "#0"},
				"south": {"uv": [1, 12.375, 1.125, 12.875], "texture": "#0"},
				"west": {"uv": [11, 12.125, 11.5, 12.625], "texture": "#0"},
				"up": {"uv": [1.25, 12.875, 1.125, 12.375], "texture": "#0"},
				"down": {"uv": [1.375, 12.375, 1.25, 12.875], "texture": "#0"}
			}
		},
		{
			"from": [-5.096, -3.63373, -0.12969],
			"to": [-3.404, -2.13373, 1.37031],
			"rotation": {"angle": 0, "axis": "y", "origin": [-4.24125, -1.77178, 1.0944]},
			"faces": {
				"north": {"uv": [4.625, 12.375, 4.875, 12.625], "texture": "#0"},
				"east": {"uv": [4.875, 12.375, 5.125, 12.625], "texture": "#0"},
				"south": {"uv": [5.125, 12.375, 5.375, 12.625], "texture": "#0"},
				"west": {"uv": [5.375, 12.375, 5.625, 12.625], "texture": "#0"},
				"up": {"uv": [5.875, 12.625, 5.625, 12.375], "texture": "#0"},
				"down": {"uv": [6.125, 12.375, 5.875, 12.625], "texture": "#0"}
			}
		},
		{
			"from": [-5.064, -2.63373, 0.71631],
			"to": [-3.436, 0.11627, 2.71631],
			"rotation": {"angle": 0, "axis": "y", "origin": [-4.24125, -1.77178, 1.1904]},
			"faces": {
				"north": {"uv": [12.125, 12.25, 12.375, 12.625], "texture": "#0"},
				"east": {"uv": [12.25, 5.875, 12.5, 6.25], "texture": "#0"},
				"south": {"uv": [12.25, 6.25, 12.5, 6.625], "texture": "#0"},
				"west": {"uv": [12.25, 9.875, 12.5, 10.25], "texture": "#0"},
				"up": {"uv": [12.625, 12.625, 12.375, 12.375], "texture": "#0"},
				"down": {"uv": [12.625, 10.25, 12.375, 10.5], "texture": "#0"}
			}
		},
		{
			"from": [-5.442, -0.34567, 0.29697],
			"to": [-3.09, 0.40433, 3.23297],
			"rotation": {"angle": 0, "axis": "y", "origin": [-4.24125, -1.77178, 1.1904]},
			"faces": {
				"north": {"uv": [12.375, 12.25, 12.625, 12.375], "texture": "#0"},
				"east": {"uv": [3, 12.5, 3.25, 12.625], "texture": "#0"},
				"south": {"uv": [3.25, 12.5, 3.5, 12.625], "texture": "#0"},
				"west": {"uv": [3.5, 12.5, 3.75, 12.625], "texture": "#0"},
				"up": {"uv": [4.375, 12.625, 4.125, 12.375], "texture": "#0"},
				"down": {"uv": [4.625, 12.375, 4.375, 12.625], "texture": "#0"}
			}
		},
		{
			"from": [19.16, -4.974, 7.564],
			"to": [20.41, -0.974, 11.564],
			"rotation": {"angle": -22.5, "axis": "y", "origin": [19.75875, -1.77178, 10.1904]},
			"faces": {
				"north": {"uv": [0.875, 12.375, 1, 12.875], "texture": "#0"},
				"east": {"uv": [3.25, 9.25, 3.75, 9.75], "texture": "#0"},
				"south": {"uv": [1, 12.375, 1.125, 12.875], "texture": "#0"},
				"west": {"uv": [11, 12.125, 11.5, 12.625], "texture": "#0"},
				"up": {"uv": [1.25, 12.875, 1.125, 12.375], "texture": "#0"},
				"down": {"uv": [1.375, 12.375, 1.25, 12.875], "texture": "#0"}
			}
		},
		{
			"from": [18.904, -3.63373, 8.87031],
			"to": [20.596, -2.13373, 10.37031],
			"rotation": {"angle": -22.5, "axis": "y", "origin": [19.75875, -1.77178, 10.0944]},
			"faces": {
				"north": {"uv": [4.625, 12.375, 4.875, 12.625], "texture": "#0"},
				"east": {"uv": [4.875, 12.375, 5.125, 12.625], "texture": "#0"},
				"south": {"uv": [5.125, 12.375, 5.375, 12.625], "texture": "#0"},
				"west": {"uv": [5.375, 12.375, 5.625, 12.625], "texture": "#0"},
				"up": {"uv": [5.875, 12.625, 5.625, 12.375], "texture": "#0"},
				"down": {"uv": [6.125, 12.375, 5.875, 12.625], "texture": "#0"}
			}
		},
		{
			"from": [18.936, -2.63373, 9.71631],
			"to": [20.564, 0.11627, 11.71631],
			"rotation": {"angle": -22.5, "axis": "y", "origin": [19.75875, -1.77178, 10.1904]},
			"faces": {
				"north": {"uv": [12.125, 12.25, 12.375, 12.625], "texture": "#0"},
				"east": {"uv": [12.25, 5.875, 12.5, 6.25], "texture": "#0"},
				"south": {"uv": [12.25, 6.25, 12.5, 6.625], "texture": "#0"},
				"west": {"uv": [12.25, 9.875, 12.5, 10.25], "texture": "#0"},
				"up": {"uv": [12.625, 12.625, 12.375, 12.375], "texture": "#0"},
				"down": {"uv": [12.625, 10.25, 12.375, 10.5], "texture": "#0"}
			}
		},
		{
			"from": [18.558, -0.34567, 9.29697],
			"to": [20.91, 0.40433, 12.23297],
			"rotation": {"angle": -22.5, "axis": "y", "origin": [19.75875, -1.77178, 10.1904]},
			"faces": {
				"north": {"uv": [12.375, 12.25, 12.625, 12.375], "texture": "#0"},
				"east": {"uv": [3, 12.5, 3.25, 12.625], "texture": "#0"},
				"south": {"uv": [3.25, 12.5, 3.5, 12.625], "texture": "#0"},
				"west": {"uv": [3.5, 12.5, 3.75, 12.625], "texture": "#0"},
				"up": {"uv": [4.375, 12.625, 4.125, 12.375], "texture": "#0"},
				"down": {"uv": [4.625, 12.375, 4.375, 12.625], "texture": "#0"}
			}
		},
		{
			"from": [-4.84, -4.974, 7.564],
			"to": [-3.59, -0.974, 11.564],
			"rotation": {"angle": 0, "axis": "y", "origin": [-4.24125, -1.77178, 10.1904]},
			"faces": {
				"north": {"uv": [0.875, 12.375, 1, 12.875], "texture": "#0"},
				"east": {"uv": [3.25, 9.25, 3.75, 9.75], "texture": "#0"},
				"south": {"uv": [1, 12.375, 1.125, 12.875], "texture": "#0"},
				"west": {"uv": [11, 12.125, 11.5, 12.625], "texture": "#0"},
				"up": {"uv": [1.25, 12.875, 1.125, 12.375], "texture": "#0"},
				"down": {"uv": [1.375, 12.375, 1.25, 12.875], "texture": "#0"}
			}
		},
		{
			"from": [-5.096, -3.63373, 8.87031],
			"to": [-3.404, -2.13373, 10.37031],
			"rotation": {"angle": 0, "axis": "y", "origin": [-4.24125, -1.77178, 10.0944]},
			"faces": {
				"north": {"uv": [4.625, 12.375, 4.875, 12.625], "texture": "#0"},
				"east": {"uv": [4.875, 12.375, 5.125, 12.625], "texture": "#0"},
				"south": {"uv": [5.125, 12.375, 5.375, 12.625], "texture": "#0"},
				"west": {"uv": [5.375, 12.375, 5.625, 12.625], "texture": "#0"},
				"up": {"uv": [5.875, 12.625, 5.625, 12.375], "texture": "#0"},
				"down": {"uv": [6.125, 12.375, 5.875, 12.625], "texture": "#0"}
			}
		},
		{
			"from": [-5.064, -2.63373, 9.71631],
			"to": [-3.436, 0.11627, 11.71631],
			"rotation": {"angle": 0, "axis": "y", "origin": [-4.24125, -1.77178, 10.1904]},
			"faces": {
				"north": {"uv": [12.125, 12.25, 12.375, 12.625], "texture": "#0"},
				"east": {"uv": [12.25, 5.875, 12.5, 6.25], "texture": "#0"},
				"south": {"uv": [12.25, 6.25, 12.5, 6.625], "texture": "#0"},
				"west": {"uv": [12.25, 9.875, 12.5, 10.25], "texture": "#0"},
				"up": {"uv": [12.625, 12.625, 12.375, 12.375], "texture": "#0"},
				"down": {"uv": [12.625, 10.25, 12.375, 10.5], "texture": "#0"}
			}
		},
		{
			"from": [-5.442, -0.34567, 9.29697],
			"to": [-3.09, 0.40433, 12.23297],
			"rotation": {"angle": 0, "axis": "y", "origin": [-4.24125, -1.77178, 10.1904]},
			"faces": {
				"north": {"uv": [12.375, 12.25, 12.625, 12.375], "texture": "#0"},
				"east": {"uv": [3, 12.5, 3.25, 12.625], "texture": "#0"},
				"south": {"uv": [3.25, 12.5, 3.5, 12.625], "texture": "#0"},
				"west": {"uv": [3.5, 12.5, 3.75, 12.625], "texture": "#0"},
				"up": {"uv": [4.375, 12.625, 4.125, 12.375], "texture": "#0"},
				"down": {"uv": [4.625, 12.375, 4.375, 12.625], "texture": "#0"}
			}
		},
		{
			"from": [19.16, -4.974, -1.436],
			"to": [20.41, -0.974, 2.564],
			"rotation": {"angle": 0, "axis": "y", "origin": [19.75875, -1.77178, 1.1904]},
			"faces": {
				"north": {"uv": [0.875, 12.375, 1, 12.875], "texture": "#0"},
				"east": {"uv": [3.25, 9.25, 3.75, 9.75], "texture": "#0"},
				"south": {"uv": [1, 12.375, 1.125, 12.875], "texture": "#0"},
				"west": {"uv": [11, 12.125, 11.5, 12.625], "texture": "#0"},
				"up": {"uv": [1.25, 12.875, 1.125, 12.375], "texture": "#0"},
				"down": {"uv": [1.375, 12.375, 1.25, 12.875], "texture": "#0"}
			}
		},
		{
			"from": [18.904, -3.63373, -0.12969],
			"to": [20.596, -2.13373, 1.37031],
			"rotation": {"angle": 0, "axis": "y", "origin": [19.75875, -1.77178, 1.0944]},
			"faces": {
				"north": {"uv": [4.625, 12.375, 4.875, 12.625], "texture": "#0"},
				"east": {"uv": [4.875, 12.375, 5.125, 12.625], "texture": "#0"},
				"south": {"uv": [5.125, 12.375, 5.375, 12.625], "texture": "#0"},
				"west": {"uv": [5.375, 12.375, 5.625, 12.625], "texture": "#0"},
				"up": {"uv": [5.875, 12.625, 5.625, 12.375], "texture": "#0"},
				"down": {"uv": [6.125, 12.375, 5.875, 12.625], "texture": "#0"}
			}
		},
		{
			"from": [18.936, -2.63373, 0.71631],
			"to": [20.564, 0.11627, 2.71631],
			"rotation": {"angle": 0, "axis": "y", "origin": [19.75875, -1.77178, 1.1904]},
			"faces": {
				"north": {"uv": [12.125, 12.25, 12.375, 12.625], "texture": "#0"},
				"east": {"uv": [12.25, 5.875, 12.5, 6.25], "texture": "#0"},
				"south": {"uv": [12.25, 6.25, 12.5, 6.625], "texture": "#0"},
				"west": {"uv": [12.25, 9.875, 12.5, 10.25], "texture": "#0"},
				"up": {"uv": [12.625, 12.625, 12.375, 12.375], "texture": "#0"},
				"down": {"uv": [12.625, 10.25, 12.375, 10.5], "texture": "#0"}
			}
		},
		{
			"from": [18.558, -0.34567, 0.29697],
			"to": [20.91, 0.40433, 3.23297],
			"rotation": {"angle": 0, "axis": "y", "origin": [19.75875, -1.77178, 1.1904]},
			"faces": {
				"north": {"uv": [12.375, 12.25, 12.625, 12.375], "texture": "#0"},
				"east": {"uv": [3, 12.5, 3.25, 12.625], "texture": "#0"},
				"south": {"uv": [3.25, 12.5, 3.5, 12.625], "texture": "#0"},
				"west": {"uv": [3.5, 12.5, 3.75, 12.625], "texture": "#0"},
				"up": {"uv": [4.375, 12.625, 4.125, 12.375], "texture": "#0"},
				"down": {"uv": [4.625, 12.375, 4.375, 12.625], "texture": "#0"}
			}
		},
		{
			"from": [-7.436, 18.5, -2.5],
			"to": [23.436, 20.25, 16.75],
			"rotation": {"angle": 0, "axis": "y", "origin": [6.564, 29.75, 6.5]},
			"faces": {
				"north": {"uv": [11.75, 7.375, 15.75, 7.625], "texture": "#0"},
				"east": {"uv": [12, 1.5, 14.375, 1.75], "texture": "#0"},
				"south": {"uv": [12, 0, 16, 0.25], "texture": "#0"},
				"west": {"uv": [12, 1.75, 14.375, 2], "texture": "#0"},
				"up": {"uv": [8.25, 6.625, 4.25, 4.25], "texture": "#0"},
				"down": {"uv": [8.25, 0, 4.25, 2.375], "texture": "#0"}
			}
		},
		{
			"from": [-7, 1.5, -1.5],
			"to": [23, 17.75, 15],
			"rotation": {"angle": 0, "axis": "y", "origin": [6.5, 8.25, 6]},
			"faces": {
				"north": {"uv": [8.25, 0, 12, 2], "texture": "#0"},
				"east": {"uv": [0, 9.25, 2.125, 11.25], "texture": "#0"},
				"south": {"uv": [8.25, 2, 12, 4], "texture": "#0"},
				"west": {"uv": [2.125, 9.875, 4.25, 11.875], "texture": "#0"},
				"up": {"uv": [3.75, 9.25, 0, 7.125], "texture": "#0"},
				"down": {"uv": [11.5, 7.75, 7.75, 9.875], "texture": "#0"}
			}
		},
		{
			"from": [-7.282, 15.25, 11.75],
			"to": [23.282, 19.5, 13.25],
			"rotation": {"angle": 22.5, "axis": "x", "origin": [7.75, 11.375, 12.5]},
			"faces": {
				"north": {"uv": [11.5, 8.25, 15.375, 8.75], "texture": "#0"},
				"east": {"uv": [11.5, 12.25, 11.75, 12.75], "texture": "#0"},
				"south": {"uv": [11.5, 8.75, 15.375, 9.25], "texture": "#0"},
				"west": {"uv": [11.75, 12.25, 12, 12.75], "texture": "#0"},
				"up": {"uv": [15.875, 0.5, 12, 0.25], "texture": "#0"},
				"down": {"uv": [15.875, 0.5, 12, 0.75], "texture": "#0"}
			}
		},
		{
			"from": [-7.314, 14.66802, -1.82419],
			"to": [23.314, 18.91802, 14.67581],
			"rotation": {"angle": 0, "axis": "x", "origin": [7.718, 16.79302, 13.92581]},
			"faces": {
				"north": {"uv": [11.5, 9.25, 15.375, 9.75], "texture": "#0"},
				"east": {"uv": [0, 11.25, 2.125, 11.75], "texture": "#0"},
				"south": {"uv": [4.25, 11.75, 8.125, 12.25], "texture": "#0"},
				"west": {"uv": [0, 11.75, 2.125, 12.25], "texture": "#0"},
				"up": {"uv": [3.875, 7.125, 0, 5], "texture": "#0"},
				"down": {"uv": [7.75, 6.625, 3.875, 8.75], "texture": "#0"}
			}
		},
		{
			"from": [-6, 0.25, -0.5],
			"to": [22, 1.5, 14],
			"rotation": {"angle": 0, "axis": "y", "origin": [6.5, 7.25, 6]},
			"faces": {
				"north": {"uv": [11.5, 9.75, 15, 9.875], "texture": "#0"},
				"east": {"uv": [11.5, 12.125, 13.375, 12.25], "texture": "#0"},
				"south": {"uv": [11.75, 7.625, 15.25, 7.75], "texture": "#0"},
				"west": {"uv": [0, 12.25, 1.875, 12.375], "texture": "#0"},
				"up": {"uv": [7.75, 4.25, 4.25, 2.375], "texture": "#0"},
				"down": {"uv": [11.75, 4, 8.25, 5.875], "texture": "#0"}
			}
		},
		{
			"from": [-7.75, 13.32, 3.5],
			"to": [-7, 17.82, 8.5],
			"rotation": {"angle": 0, "axis": "y", "origin": [-22.25, 8.32, -6]},
			"faces": {
				"north": {"uv": [12.25, 10.25, 12.375, 10.875], "texture": "#0"},
				"east": {"uv": [3.25, 11.875, 3.875, 12.5], "texture": "#0"},
				"south": {"uv": [12.25, 10.875, 12.375, 11.5], "texture": "#0"},
				"west": {"uv": [8.125, 12.125, 8.75, 12.75], "texture": "#0"},
				"up": {"uv": [0.125, 13, 0, 12.375], "texture": "#0"},
				"down": {"uv": [0.25, 12.375, 0.125, 13], "texture": "#0"}
			}
		},
		{
			"from": [23, 13.32, 3.5],
			"to": [23.75, 17.82, 8.5],
			"rotation": {"angle": 0, "axis": "y", "origin": [38.25, 8.32, -6]},
			"faces": {
				"north": {"uv": [12.375, 10.25, 12.25, 10.875], "texture": "#0"},
				"east": {"uv": [8.75, 12.125, 8.125, 12.75], "texture": "#0"},
				"south": {"uv": [12.375, 10.875, 12.25, 11.5], "texture": "#0"},
				"west": {"uv": [3.875, 11.875, 3.25, 12.5], "texture": "#0"},
				"up": {"uv": [0, 13, 0.125, 12.375], "texture": "#0"},
				"down": {"uv": [0.125, 12.375, 0.25, 13], "texture": "#0"}
			}
		},
		{
			"from": [-8.25, 17.82, 2.5],
			"to": [-7, 18.82, 11],
			"rotation": {"angle": 0, "axis": "y", "origin": [-22.75, 9.32, -0.5]},
			"faces": {
				"north": {"uv": [8.125, 4.125, 8.25, 4.25], "texture": "#0"},
				"east": {"uv": [3.875, 12.25, 5, 12.375], "texture": "#0"},
				"south": {"uv": [3.625, 9.75, 3.75, 9.875], "texture": "#0"},
				"west": {"uv": [5, 12.25, 6.125, 12.375], "texture": "#0"},
				"up": {"uv": [3.875, 8.25, 3.75, 7.125], "texture": "#0"},
				"down": {"uv": [2, 12.25, 1.875, 13.375], "texture": "#0"}
			}
		},
		{
			"from": [23, 17.82, 2.5],
			"to": [24.25, 18.82, 11],
			"rotation": {"angle": 0, "axis": "y", "origin": [38.75, 9.32, -0.5]},
			"faces": {
				"north": {"uv": [8.25, 4.125, 8.125, 4.25], "texture": "#0"},
				"east": {"uv": [6.125, 12.25, 5, 12.375], "texture": "#0"},
				"south": {"uv": [3.75, 9.75, 3.625, 9.875], "texture": "#0"},
				"west": {"uv": [5, 12.25, 3.875, 12.375], "texture": "#0"},
				"up": {"uv": [3.75, 8.25, 3.875, 7.125], "texture": "#0"},
				"down": {"uv": [1.875, 12.25, 2, 13.375], "texture": "#0"}
			}
		},
		{
			"from": [-7.468, 16.5, -2.5],
			"to": [-6.468, 18.5, 1],
			"rotation": {"angle": 0, "axis": "y", "origin": [-21.468, 8, -9.5]},
			"faces": {
				"north": {"uv": [2.75, 12.5, 2.875, 12.75], "texture": "#0"},
				"east": {"uv": [7, 12.25, 7.5, 12.5], "texture": "#0"},
				"south": {"uv": [2.875, 12.5, 3, 12.75], "texture": "#0"},
				"west": {"uv": [7.5, 12.25, 8, 12.5], "texture": "#0"},
				"up": {"uv": [1.5, 12.875, 1.375, 12.375], "texture": "#0"},
				"down": {"uv": [1.625, 12.375, 1.5, 12.875], "texture": "#0"}
			}
		},
		{
			"from": [22.404, 16.5, -2.5],
			"to": [23.404, 18.5, 1],
			"rotation": {"angle": 0, "axis": "y", "origin": [37.404, 8, -9.5]},
			"faces": {
				"north": {"uv": [2.875, 12.5, 2.75, 12.75], "texture": "#0"},
				"east": {"uv": [8, 12.25, 7.5, 12.5], "texture": "#0"},
				"south": {"uv": [3, 12.5, 2.875, 12.75], "texture": "#0"},
				"west": {"uv": [7.5, 12.25, 7, 12.5], "texture": "#0"},
				"up": {"uv": [1.375, 12.875, 1.5, 12.375], "texture": "#0"},
				"down": {"uv": [1.5, 12.375, 1.625, 12.875], "texture": "#0"}
			}
		},
		{
			"from": [-8.5, 14.07, 5.25],
			"to": [-7.75, 15.57, 6.75],
			"rotation": {"angle": 0, "axis": "x", "origin": [-8.125, 14.82, 6]},
			"faces": {
				"north": {"uv": [2.25, 12.5, 2.375, 12.75], "texture": "#0"},
				"east": {"uv": [12.25, 11.5, 12.5, 11.75], "texture": "#0"},
				"south": {"uv": [2.375, 12.5, 2.5, 12.75], "texture": "#0"},
				"west": {"uv": [0.25, 12.375, 0.5, 12.625], "texture": "#0"},
				"up": {"uv": [2.625, 12.75, 2.5, 12.5], "texture": "#0"},
				"down": {"uv": [2.75, 12.5, 2.625, 12.75], "texture": "#0"}
			}
		},
		{
			"from": [23.75, 14.07, 5.25],
			"to": [24.5, 15.57, 6.75],
			"rotation": {"angle": 0, "axis": "x", "origin": [24.125, 14.82, 6]},
			"faces": {
				"north": {"uv": [2.375, 12.5, 2.25, 12.75], "texture": "#0"},
				"east": {"uv": [0.5, 12.375, 0.25, 12.625], "texture": "#0"},
				"south": {"uv": [2.5, 12.5, 2.375, 12.75], "texture": "#0"},
				"west": {"uv": [12.5, 11.5, 12.25, 11.75], "texture": "#0"},
				"up": {"uv": [2.5, 12.75, 2.625, 12.5], "texture": "#0"},
				"down": {"uv": [2.625, 12.5, 2.75, 12.75], "texture": "#0"}
			}
		}
	],
	"display": {
		"thirdperson_righthand": {
			"rotation": [90, 0, 0],
			"translation": [-6, -3.5, 4],
			"scale": [1.3, 1.3, 1.3]
		},
		"gui": {
			"rotation": [21, 153, 0],
			"translation": [0, -1.25, 0],
			"scale": [0.4, 0.4, 0.4]
		}
	},
	"groups": [
		{
			"name": "group",
			"origin": [7.968, 9.7639, 5.64347],
			"children": [0, 1, 2, 3, 4, 5, 6, 7, 8, 9, 10, 11, 12, 13, 14]
		},
		{
			"name": "group",
			"origin": [-4.24125, -1.77178, 1.1904],
			"children": [15, 16, 17, 18]
		},
		{
			"name": "group",
			"origin": [-4.24125, -1.77178, 1.1904],
			"children": [19, 20, 21, 22]
		},
		{
			"name": "group",
			"origin": [-4.24125, -1.77178, 1.1904],
			"children": [23, 24, 25, 26]
		},
		{
			"name": "group",
			"origin": [-4.24125, -1.77178, 1.1904],
			"children": [27, 28, 29, 30]
		},
		{
			"name": "group",
			"origin": [24.125, 14.82, 6],
			"children": [31, 32, 33, 34, 35, 36, 37, 38, 39, 40, 41, 42, 43]
		}
	]
}